{
  "aubrylieutier" : {
    "communications" : [ {
      "desription" : "Photo dans Architecture d’Aujourd’hui n°432",
      "id" : 236,
      "image" : "19.png",
      "projet" : "Foyer Mélanie (16 septembre 2019)"
    }, {
      "desription" : "Récompense : prix les rubans du patrimoine",
      "id" : 235,
      "image" : "20.png",
      "projet" : "Espace Culturel et Touristique à Marlenheim (3 juin 2019)"
    }, {
      "desription" : "Construction moderne",
      "id" : 234,
      "image" : "21.png",
      "projet" : "Cœur des Tanneries à Lingolsheim (Juin 2018)"
    }, {
      "desription" : "Lauréat du prix archi design club awards",
      "id" : 233,
      "image" : "22.png",
      "projet" : "Cœur des Tanneries à Lingolsheim (8 janvier 2018)"
    }, {
      "desription" : "Affiche d’exposition CAUE",
      "id" : 232,
      "image" : "23.png",
      "projet" : "Écoles Molkenbronn (2017)"
    }, {
      "desription" : "Palmarès de la construction bois",
      "id" : 231,
      "image" : "24.png",
      "projet" : "Dépendance à Rosheim (2017)"
    }, {
      "desription" : "Projet sélectionné parmi les 100 bâtiments de l’année AMC 2017",
      "id" : 230,
      "image" : "25.png",
      "projet" : "Cœur des Tanneries à Lingolsheim (2017)"
    }, {
      "desription" : "Projet sélectionné parmi les 100 bâtiments de l’année AMC 2017",
      "id" : 229,
      "image" : "25.png",
      "projet" : "Cœur des Tanneries à Lingolsheim (2017)"
    }, {
      "desription" : "Exposition trinationale 2017. Maison Européenne de l’Architecture",
      "id" : 228,
      "image" : "26.png",
      "projet" : "Cœur des Tanneries à Lingolsheim (Octobre 2017)"
    }, {
      "desription" : "Exposition trinationale 2017",
      "id" : 227,
      "image" : "26.png",
      "projet" : "Cœur des Tanneries à Lingolsheim (Octobre 2017)"
    }, {
      "desription" : "Exposition CAUE",
      "id" : 226,
      "image" : "27.png",
      "projet" : "École de Bischoffsheim (15 juin 2017)"
    }, {
      "desription" : "Projets sélectionnés. Palmarès de l'architecture et de l'aménagement urbain",
      "id" : 225,
      "image" : "28.png",
      "projet" : "Foyer Mélanie, école Molkenbronn, maison des services Truchtersheim (2016)"
    }, {
      "desription" : "Exposition trinationale 2016. Maison Européenne de l'Architecture",
      "id" : 224,
      "image" : "29.png",
      "projet" : "Mairie de Knoersheim (Octobre 2016)"
    }, {
      "desription" : "Exposition trinationale 2016. Maison Européenne de l'Architecture",
      "id" : 223,
      "image" : "30.png",
      "projet" : "Ecole de Nordheim (Octobre 2016)"
    }, {
      "desription" : "projet : Foyer Paroissial de la Robertsau architecte(s) : AUBRY LIEUTIER",
      "id" : 222,
      "image" : "18.png",
      "projet" : "Prix Equerre d'Argent 2015 \"Les 100 bâtiments de l'année\""
    }, {
      "desription" : "projet : Foyer Paroissial de la Robertsau architecte(s) : AUBRY LIEUTIER",
      "id" : 221,
      "image" : "17.png",
      "projet" : "Projet sélectionné pour le prix du Projet Citoyen 2015 de l'UNSFA"
    }, {
      "desription" : "proarticle de : Le Moniteur du BTP",
      "id" : 220,
      "image" : "31.png",
      "projet" : "Foyer Mélanie (24 octobre 2014)"
    }, {
      "desription" : "projet : Foyer Paroissial de la Robertsau architecte(s) : AUBRY LIEUTIER. article de : Le Moniteur du BTP",
      "id" : 219,
      "image" : "16.png",
      "projet" : "Elégance et épure pour le foyer de la Robertsau (2014)"
    }, {
      "desription" : "projet : Chalet du Champ du Feu à Belmont architecte(s) : AUBRY LIEUTIER. article de : Le Moniteur du BTP",
      "id" : 218,
      "image" : "15.png",
      "projet" : "Coup de jeune à la station de ski du Champ du Feu (2013)"
    }, {
      "desription" : "Projet sélectionné parmi les 100 bâtiments de l'année AMC 2007",
      "id" : 217,
      "image" : "32.png",
      "projet" : "Collège de la Wantzenau (2007)"
    }, {
      "desription" : "projet : Collège André-MALRAUX architecte(s) : AUBRY LIEUTIER. article de : DNA",
      "id" : 216,
      "image" : "14.png",
      "projet" : "Des idées dans les murs (2007)"
    }, {
      "desription" : "projet : Présentation. article de : Vincent Lieutier",
      "id" : 215,
      "image" : "13.png",
      "projet" : "Autoportraits de 12 agences (2006)"
    }, {
      "desription" : "projet : CLSH ECKBOLSHEIM architecte(s) : Cabinet HEINTZ-KEHR. article de : Vincent Lieutier",
      "id" : 214,
      "image" : "12.png",
      "projet" : "C'est peut-être ça, l'achitecture (2005)"
    }, {
      "desription" : "projet : Le Courlis architecte(s) : AUBRY LIEUTIER. article de : Vincent Lieutier",
      "id" : 213,
      "image" : "11.png",
      "projet" : "Prix de l'architecture Grand Est (2005)"
    }, {
      "desription" : "projet : Le Courlis architecte(s) : AUBRY LIEUTIER. article de : DNA",
      "id" : 212,
      "image" : "10.png",
      "projet" : "L'architecture récompensée (2005)"
    }, {
      "desription" : "Lauréat du palmarès de l'Architecture et de l'aménagement.",
      "id" : 211,
      "image" : "33.png",
      "projet" : "Herbsheim (2004)"
    }, {
      "desription" : "projet : Musée du Pays de Sarrebourg architecte(s) : Bernard DESMOULIN. article de : Thierry AUBRY",
      "id" : 210,
      "image" : "9.png",
      "projet" : "Souffle intérieur (2004)"
    }, {
      "desription" : "projet : IUT de Colmar architecte(s) : TOA ARCHITECTES. article de : Vincent Lieutier",
      "id" : 209,
      "image" : "8.png",
      "projet" : "Les deux cotés du mur (2004)"
    }, {
      "desription" : "projet : Le Courlis architecte(s) : AUBRY LIEUTIER. Projet sélectionné",
      "id" : 208,
      "image" : "7.png",
      "projet" : "Palmarès de l'architecte et de l'aménagement urbain Alsace (2004)"
    }, {
      "desription" : "projet : Le Courlis architecte(s) : AUBRY LIEUTIER. article de : Emmanuelle ROMBACH",
      "id" : 207,
      "image" : "6.png",
      "projet" : "Agglo et Polycarbo (2003)"
    }, {
      "desription" : "projet : La Coupole à Saint-Louis architecte(s) : Manuelle GAUTRAND. article de : Vincent Lieutier",
      "id" : 206,
      "image" : "5.png",
      "projet" : "AUn projet de gonzesse (2002)"
    }, {
      "desription" : "projet : Salle Concordia architecte(s) : AUBRY LIEUTIER. article de : Vincent Lieutier",
      "id" : 205,
      "image" : "4.png",
      "projet" : "Les Journées de l'architecture - parole aux usagers (2002)"
    }, {
      "desription" : "projet : Salle Concordia architecte(s) : AUBRY LIEUTIER. article de : Vincent Lieutier",
      "id" : 204,
      "image" : "3.png",
      "projet" : "L'architecture comtemporaine expliquée au nuls (2001)"
    }, {
      "desription" : "projet : La Coupole à Saint-Louis architecte(s) : Manuelle GAUTRAND. article de : Vincent Lieutier",
      "id" : 203,
      "image" : "2.png",
      "projet" : "La Coupole de Saint Louis (2000)"
    }, {
      "desription" : "projet : Stadium de Vitrolles architecte(s) : Rudy RICCIOTTI. article de : \"Moins cher qu'un HLM\"",
      "id" : 202,
      "image" : "1.png",
      "projet" : "Les interviews vitriol d'un sudiste (1999)"
    }, {
      "desription" : "projet : Journal. article de : Vincent Lieutier, Christophe Flachaire et Eric Dussol",
      "id" : 201,
      "image" : "0.png",
      "projet" : "Moins cher qu'un HLM (1994)"
    } ],
    "concours" : [ {
      "desription" : "",
      "id" : 131,
      "image" : "2019_hoerdt.png",
      "projet" : "Collège Baldung Grien - Hoerdt (67) 2019-2021"
    }, {
      "desription" : "",
      "id" : 130,
      "image" : "2019_schweighouse.png",
      "projet" : "Mairie et place de la Mairie - Schweighouse-sur-Moder (67) 2018-2020"
    }, {
      "desription" : "",
      "id" : 129,
      "image" : "2019_kertzfeld.png",
      "projet" : "Périscolaire - Kertzfeld (67) 2017-2019"
    }, {
      "desription" : "",
      "id" : 128,
      "image" : "2020_truchtersheim.png",
      "projet" : "Maison des Services Publics du Kochersberg 2 - Truchtersheim (67) 2017-2020"
    }, {
      "desription" : "",
      "id" : 127,
      "image" : "2017_2019_Bootzheim.png",
      "projet" : "Accueil périscolaire - Bootzheim (67) 2017-2020"
    }, {
      "desription" : "",
      "id" : 126,
      "image" : "2015_Wasselonne.png",
      "projet" : "Centre d'Incendie et de Secours - Wasselonne (67) 2016-2018"
    }, {
      "desription" : "",
      "id" : 125,
      "image" : "2015_Weyersheim.png",
      "projet" : "Le Trait d'Union, salle de spectacle, bibliothèque - Weyerhseim (67) 2016-2019"
    }, {
      "desription" : "Projet primé au Palmarès de la construction Bois Région Grand Est 2017, deuxième prix.",
      "id" : 124,
      "image" : "2015_Rosheim.png",
      "projet" : "Extension de la maison A, bureau, piscine, pool-house - Rosheim (67) 2014-2015"
    }, {
      "desription" : "",
      "id" : 123,
      "image" : "2014_Tanneries_logements.png",
      "projet" : "Logements - Lingolsheim (67) 2014-2017 en association avec Richter architectes"
    }, {
      "desription" : "Projet lauréat ArchiDesignclub Awards 2018 dans la catégorie programme mixte. Projet sélectionné parmi les 100 bâtiments de l’année AMC 2017. Exposition trinationale 2017 Maison Européenne de l’Architecture.",
      "id" : 122,
      "image" : "2014_Tanneries.png",
      "projet" : "Groupe scolaire, IME et Gymnase - Lingolsheim (67) 2014 -2017 en association avec Richter architectes"
    }, {
      "description" : "",
      "id" : 121,
      "image" : "2013_Marlenheim.png",
      "projet" : "Office de Tourisme - Marlenheim(67) 2013-2018"
    }, {
      "description" : "Exposition trinationale 2016 Maison Européenne de l’Architecture.",
      "id" : 120,
      "image" : "2015_Knoersheim.png",
      "projet" : "Mairie - Knoersheim(67) 2013-2015"
    }, {
      "description" : "Exposition trinationale 2016 Maison Européenne de l’Architecture.",
      "id" : 119,
      "image" : "2012_2015_Nordheim.png",
      "projet" : "Groupe scolaire et périscolaire ALSH - Nordheim(67) 2012-2015"
    }, {
      "description" : "Exposition trinationale 2016 Maison Européenne de l’Architecture.",
      "id" : 118,
      "image" : "2014_Marmoutier.png",
      "projet" : "Ecole primaire - Marmoutier(67) 2012-2014"
    }, {
      "description" : "Projet sélectionné au Palmarès de l’Architecture et de l’Aménagement en Alsace 2016.",
      "id" : 117,
      "image" : "2011_Molkenbronn.png",
      "projet" : "Groupe Scolaire de Molkenbronn - Lingolsheim(67) 2011-2014"
    }, {
      "description" : "Projet sélectionné parmi les 100 bâtiments de l’année AMC 2015. Projet sélectionné au Prix du Projet Citoyen 2015. Projet sélectionné au Palmarès de l’Architecture et de l’Aménagement en Alsace 2016.",
      "id" : 116,
      "image" : "2011_Paroisse.png",
      "projet" : "Foyer protestant Mélanie de la Robertsau - Strasbourg(67) 2011-2013"
    }, {
      "description" : "",
      "id" : 115,
      "image" : "2010_Belmont.png",
      "projet" : "Chalet du Champ du Feu - Belmont(67) 2010-2012"
    }, {
      "description" : "",
      "id" : 114,
      "image" : "2012_Charlotte.png",
      "projet" : "Maison Charlotte et Louis - 2012"
    }, {
      "description" : "",
      "id" : 113,
      "image" : "2009_Molsheim.png",
      "projet" : "Centre d'Incendie et de Secours - Molsheim(67) 2009-2012"
    }, {
      "description" : "",
      "id" : 112,
      "image" : "2008_Selestat.png",
      "projet" : "Collège Jean Mentel - Sélestat(67) 2008-2012"
    }, {
      "description" : "Projet sélectionné au Palmarès de l’Architecture et de l’Aménagement en Alsace 2016.",
      "id" : 111,
      "image" : "2008_Truchtersheim.png",
      "projet" : "Maison des Services Publics - Truchtersheim(67) 2008-2011"
    }, {
      "description" : "",
      "id" : 110,
      "image" : "2007_Lingolsheim.png",
      "projet" : "Centre Plein Air Amitié - Lingolsheim(67) 2007-2010"
    }, {
      "description" : "Coup de cœur Journées Européennes du Patrimoine 2009.",
      "id" : 109,
      "image" : "2007_Marlenheim.png",
      "projet" : "Maison Appréderis - Marlenheim(67) 2007-2009"
    }, {
      "description" : "",
      "id" : 108,
      "image" : "2006_Lyon.png",
      "projet" : "Magasin Lafaurie - Lyon(69) 2006"
    }, {
      "description" : "",
      "id" : 107,
      "image" : "2005_Rosheim.png",
      "projet" : "Gymnase Intercommunal du Collège - Rosheim(67) 2005-2008"
    }, {
      "description" : "",
      "id" : 106,
      "image" : "2005_Niederhaslach.png",
      "projet" : "Ecole maternelle et élémentaire - Niederhaslach(67) 2005-2008"
    }, {
      "description" : "",
      "id" : 105,
      "image" : "2005_Sarreguemines.png",
      "projet" : "Médiathèque - Sarreguemines(57) 2005-2007"
    }, {
      "description" : "Bâtiment sélectionné par AMC Le Moniteur Architecture, « 2007 une année d’architecture en France » n°175 janvier 2008.",
      "id" : 104,
      "image" : "2003_LaWantzenau.png",
      "projet" : "Collège André Malraux - La Wantzenau(67) 2003-2007"
    }, {
      "description" : "",
      "id" : 103,
      "image" : "2001_Danielle.png",
      "projet" : "Maison Danielle - Beauvezer(04) 2006"
    }, {
      "description" : "Lauréat du palmarès de l’architecture et de l’aménagement urbain 2005 - Alsace. Sélection Prix de l’Architecture Grand Est 2005.",
      "id" : 102,
      "image" : "2001_Herbsheim.png",
      "projet" : "Salle de Sport et Espace Culturel, primé - Herbsheim(67) 2001-2003"
    }, {
      "description" : "Sélection régionale Prix Grand Public de l’Architecture.",
      "id" : 101,
      "image" : "1999_Dauendorf.png",
      "projet" : "Salle socio-éducative - Dauendorf(67) 1999-2001"
    } ],
    "projets" : [ {
      "desription" : "",
      "id" : 331,
      "image" : "http://aubrylieutier.draconic-graphisme.com/media/proj/2019_hoerdt.png",
      "projet" : "Collège Baldung Grien - Hoerdt (67) 2019-2021"
    }, {
      "desription" : "",
      "id" : 330,
      "image" : "http://aubrylieutier.draconic-graphisme.com/media/proj/2019_schweighouse.png",
      "projet" : "Mairie et place de la Mairie - Schweighouse-sur-Moder (67) 2018-2020"
    }, {
      "desription" : "",
      "id" : 329,
      "image" : "http://aubrylieutier.draconic-graphisme.com/media/proj/2019_kertzfeld.png",
      "projet" : "Périscolaire - Kertzfeld (67) 2017-2019"
    }, {
      "desription" : "",
      "id" : 328,
      "image" : "http://aubrylieutier.draconic-graphisme.com/media/proj/2020_truchtersheim.png",
      "projet" : "Maison des Services Publics du Kochersberg 2 - Truchtersheim (67) 2017-2020"
    }, {
      "desription" : "",
      "id" : 327,
      "image" : "http://aubrylieutier.draconic-graphisme.com/media/proj/2017_2019_Bootzheim.png",
      "projet" : "Accueil périscolaire - Bootzheim (67) 2017-2020"
    }, {
      "desription" : "",
      "id" : 326,
      "image" : "http://aubrylieutier.draconic-graphisme.com/media/proj/2015_Wasselonne.png",
      "projet" : "Centre d'Incendie et de Secours - Wasselonne (67) 2016-2018"
    }, {
      "desription" : "",
      "id" : 325,
      "image" : "http://aubrylieutier.draconic-graphisme.com/media/proj/2015_Weyersheim.png",
      "projet" : "Le Trait d'Union, salle de spectacle, bibliothèque - Weyerhseim (67) 2016-2019"
    }, {
      "desription" : "Projet primé au Palmarès de la construction Bois Région Grand Est 2017, deuxième prix.",
      "id" : 324,
      "image" : "http://aubrylieutier.draconic-graphisme.com/media/proj/2015_Rosheim.png",
      "projet" : "Extension de la maison A, bureau, piscine, pool-house - Rosheim (67) 2014-2015"
    }, {
      "desription" : "",
      "id" : 323,
      "image" : "http://aubrylieutier.draconic-graphisme.com/media/proj/2014_Tanneries_logements.png",
      "projet" : "Logements - Lingolsheim (67) 2014-2017 en association avec Richter architectes"
    }, {
      "desription" : "Projet lauréat ArchiDesignclub Awards 2018 dans la catégorie programme mixte. Projet sélectionné parmi les 100 bâtiments de l’année AMC 2017. Exposition trinationale 2017 Maison Européenne de l’Architecture.",
      "id" : 322,
      "image" : "http://aubrylieutier.draconic-graphisme.com/media/proj/2014_Tanneries.png",
      "projet" : "Groupe scolaire, IME et Gymnase - Lingolsheim (67) 2014 -2017 en association avec Richter architectes"
    }, {
      "description" : "",
      "id" : 321,
      "image" : "http://aubrylieutier.draconic-graphisme.com/media/proj/2013_Marlenheim.png",
      "projet" : "Office de Tourisme - Marlenheim(67) 2013-2018"
    }, {
      "description" : "Exposition trinationale 2016 Maison Européenne de l’Architecture.",
      "id" : 320,
      "image" : "http://aubrylieutier.draconic-graphisme.com/media/proj/2015_Knoersheim.png",
      "projet" : "Mairie - Knoersheim(67) 2013-2015"
    }, {
      "description" : "Exposition trinationale 2016 Maison Européenne de l’Architecture.",
      "id" : 319,
      "image" : "http://aubrylieutier.draconic-graphisme.com/media/proj/2012_2015_Nordheim.png",
      "projet" : "Groupe scolaire et périscolaire ALSH - Nordheim(67) 2012-2015"
    }, {
      "description" : "Exposition trinationale 2016 Maison Européenne de l’Architecture.",
      "id" : 318,
      "image" : "http://aubrylieutier.draconic-graphisme.com/media/proj/2014_Marmoutier.png",
      "projet" : "Ecole primaire - Marmoutier(67) 2012-2014"
    }, {
      "description" : "Projet sélectionné au Palmarès de l’Architecture et de l’Aménagement en Alsace 2016.",
      "id" : 317,
      "image" : "http://aubrylieutier.draconic-graphisme.com/media/proj/2011_Molkenbronn.png",
      "projet" : "Groupe Scolaire de Molkenbronn - Lingolsheim(67) 2011-2014"
    }, {
      "description" : "Projet sélectionné parmi les 100 bâtiments de l’année AMC 2015. Projet sélectionné au Prix du Projet Citoyen 2015. Projet sélectionné au Palmarès de l’Architecture et de l’Aménagement en Alsace 2016.",
      "id" : 316,
      "image" : "http://aubrylieutier.draconic-graphisme.com/media/proj/2011_Paroisse.png",
      "projet" : "Foyer protestant Mélanie de la Robertsau - Strasbourg(67) 2011-2013"
    }, {
      "description" : "",
      "id" : 315,
      "image" : "http://aubrylieutier.draconic-graphisme.com/media/proj/2010_Belmont.png",
      "projet" : "Chalet du Champ du Feu - Belmont(67) 2010-2012"
    }, {
      "description" : "",
      "id" : 314,
      "image" : "http://aubrylieutier.draconic-graphisme.com/media/proj/2012_Charlotte.png",
      "projet" : "Maison Charlotte et Louis - 2012"
    }, {
      "description" : "",
      "id" : 313,
      "image" : "http://aubrylieutier.draconic-graphisme.com/media/proj/2009_Molsheim.png",
      "projet" : "Centre d'Incendie et de Secours - Molsheim(67) 2009-2012"
    }, {
      "description" : "",
      "id" : 312,
      "image" : "http://aubrylieutier.draconic-graphisme.com/media/proj/2008_Selestat.png",
      "projet" : "Collège Jean Mentel - Sélestat(67) 2008-2012"
    }, {
      "description" : "Projet sélectionné au Palmarès de l’Architecture et de l’Aménagement en Alsace 2016.",
      "id" : 311,
      "image" : "http://aubrylieutier.draconic-graphisme.com/media/proj/2008_Truchtersheim.png",
      "projet" : "Maison des Services Publics - Truchtersheim(67) 2008-2011"
    }, {
      "description" : "",
      "id" : 310,
      "image" : "http://aubrylieutier.draconic-graphisme.com/media/proj/2007_Lingolsheim.png",
      "projet" : "Centre Plein Air Amitié - Lingolsheim(67) 2007-2010"
    }, {
      "description" : "Coup de cœur Journées Européennes du Patrimoine 2009.",
      "id" : 309,
      "image" : "http://aubrylieutier.draconic-graphisme.com/media/proj/2007_Marlenheim.png",
      "projet" : "Maison Appréderis - Marlenheim(67) 2007-2009"
    }, {
      "description" : "",
      "id" : 308,
      "image" : "http://aubrylieutier.draconic-graphisme.com/media/proj/2006_Lyon.png",
      "projet" : "Magasin Lafaurie - Lyon(69) 2006"
    }, {
      "description" : "",
      "id" : 307,
      "image" : "http://aubrylieutier.draconic-graphisme.com/media/proj/2005_Rosheim.png",
      "projet" : "Gymnase Intercommunal du Collège - Rosheim(67) 2005-2008"
    }, {
      "description" : "",
      "id" : 306,
      "image" : "http://aubrylieutier.draconic-graphisme.com/media/proj/2005_Niederhaslach.png",
      "projet" : "Ecole maternelle et élémentaire - Niederhaslach(67) 2005-2008"
    }, {
      "description" : "",
      "id" : 305,
      "image" : "http://aubrylieutier.draconic-graphisme.com/media/proj/2005_Sarreguemines.png",
      "projet" : "Médiathèque - Sarreguemines(57) 2005-2007"
    }, {
      "description" : "Bâtiment sélectionné par AMC Le Moniteur Architecture, « 2007 une année d’architecture en France » n°175 janvier 2008.",
      "id" : 304,
      "image" : "http://aubrylieutier.draconic-graphisme.com/media/proj/2003_LaWantzenau.png",
      "projet" : "Collège André Malraux - La Wantzenau(67) 2003-2007"
    }, {
      "description" : "",
      "id" : 303,
      "image" : "http://aubrylieutier.draconic-graphisme.com/media/proj/2001_Danielle.png",
      "projet" : "Maison Danielle - Beauvezer(04) 2006"
    }, {
      "description" : "Lauréat du palmarès de l’architecture et de l’aménagement urbain 2005 - Alsace. Sélection Prix de l’Architecture Grand Est 2005.",
      "id" : 302,
      "image" : "http://aubrylieutier.draconic-graphisme.com/media/proj/2001_Herbsheim.png",
      "projet" : "Salle de Sport et Espace Culturel, primé - Herbsheim(67) 2001-2003"
    }, {
      "description" : "Sélection régionale Prix Grand Public de l’Architecture.",
      "id" : 301,
      "image" : "http://aubrylieutier.draconic-graphisme.com/media/proj/1999_Dauendorf.png",
      "projet" : "Salle socio-éducative - Dauendorf(67) 1999-2001"
    } ]
  }
}
